[
    {
        "token": "e793ee81f50b5b38c423e4f07a2e458b",
        "timestamp": "2026-04-15T09:29:17Z",
        "uuid": "6f8f2b31-9326-415b-9fb1-67cf9543ced3",
        "watch_time": 120,
        "video_id": "HKF4Sgqcjts",
        "ip_address": "103.171.163.208",
        "user_agent": "Mozilla/5.0 (Linux; Android 10; K) AppleWebKit/537.36 (KHTML, like Gecko) Chrome/137.0.0.0 Mobile Safari/537.36",
        "pow_verified": true,
        "request_count": 0,
        "session_hash": "eda2b0273f9a4d2a9c0ed6f718d70b5fa34146f796a56c0f3be39d26548b7303",
        "id": "69df5a6ea62b7",
        "source": "website"
    }
]