[
    {
        "token": "fa10e1b643b69cbf7fbf74efae79b3a6",
        "timestamp": "2026-05-01T00:38:34Z",
        "uuid": "740800db-8147-4018-85dd-0e4e508859d2",
        "watch_time": 300,
        "video_id": "bryR8uDRCt8",
        "ip_address": "103.168.255.71",
        "user_agent": "Mozilla/5.0 (Linux; Android 10; K) AppleWebKit/537.36 (KHTML, like Gecko) Chrome/137.0.0.0 Mobile Safari/537.36",
        "pow_verified": true,
        "request_count": 0,
        "session_hash": "a8a5c802ed707a464678e5a070c3dd22d36e38de429786a69f10ee7ca00347e2",
        "id": "69f3f60a3e184",
        "source": "website"
    }
]