[
    {
        "token": "2d9b20e9e6ac19b923f882fbbfb50e06",
        "timestamp": "2025-12-26T06:08:25Z",
        "uuid": "c7f389c3-3a6d-47ec-a493-468c99bc0816",
        "watch_time": 240,
        "video_id": "tQ3iTPxNO0U",
        "ip_address": "197.238.231.73",
        "user_agent": "Mozilla\/5.0 (Linux; Android 10; K) AppleWebKit\/537.36 (KHTML, like Gecko) Chrome\/137.0.0.0 Mobile Safari\/537.36",
        "pow_verified": true,
        "request_count": 0,
        "session_hash": "d6d27fde1265d2869eb903f12716d89b2932fa92fc037deb4f044f2227be7b36",
        "id": "694e2659e53da",
        "source": "website"
    },
    {
        "token": "26e20986b06af7db2cb495d144131efd",
        "timestamp": "2025-12-26T06:31:18Z",
        "uuid": "675bf96e-16fd-4f42-b464-cce28df59e13",
        "watch_time": 120,
        "video_id": "JYxQHCOezPE",
        "ip_address": "180.246.47.67",
        "user_agent": "Mozilla\/5.0 (Windows NT 10.0; Win64; x64) AppleWebKit\/537.36 (KHTML, like Gecko) Chrome\/143.0.0.0 Safari\/537.36",
        "pow_verified": true,
        "request_count": 0,
        "session_hash": "41d594f16070fc0e6871fb42ced830f6b401a3daee57a8a72934cf1a816cea6d",
        "id": "694e2bb6d878e",
        "source": "website"
    },
    {
        "token": "0432670db3709648e06b82527f615438",
        "timestamp": "2025-12-26T06:32:12Z",
        "uuid": "d3fd33ff-7fb7-4a39-9474-2bad2d2391b0",
        "watch_time": 120,
        "video_id": "tQ3iTPxNO0U",
        "ip_address": "103.168.190.98",
        "user_agent": "Mozilla\/5.0 (X11; Linux x86_64) AppleWebKit\/537.36 (KHTML, like Gecko) Chrome\/138.0.0.0 Safari\/537.36",
        "pow_verified": true,
        "request_count": 0,
        "session_hash": "9f12bfb3715e3cd36ddb6332fddcbfbe71a12ecf8e1387d7968da1eba22bbdfa",
        "id": "694e2becd67e3",
        "source": "website"
    },
    {
        "id": "694e41d94a922",
        "token": "74b52d74b7724e50b461b6fccaadc5dd",
        "timestamp": "2025-12-26T08:05:31.299Z",
        "source": "shortlink",
        "uuid": "24e8b59b-85dd-4cca-8000-69331c1c7cf9",
        "expires_at": "2025-12-26T10:05:31Z"
    },
    {
        "id": "694e42650dde6",
        "token": "a47d6214b040b642bccc7b0ac4debd11",
        "timestamp": "2025-12-26T08:07:58.568Z",
        "source": "shortlink",
        "uuid": "62554413-04d8-4c52-bb19-714ec47c3b8a",
        "expires_at": "2025-12-26T10:07:58Z"
    },
    {
        "token": "dd12d001811465017654bd010c0e095c",
        "timestamp": "2025-12-26T09:00:30Z",
        "uuid": "85038a44-99eb-49c1-940a-00cc65410706",
        "watch_time": 180,
        "video_id": "ky2YLjJhEWs",
        "ip_address": "103.168.190.98",
        "user_agent": "Mozilla\/5.0 (X11; Linux x86_64) AppleWebKit\/537.36 (KHTML, like Gecko) Chrome\/138.0.0.0 Safari\/537.36",
        "pow_verified": true,
        "request_count": 0,
        "session_hash": "17bff20fd290ddb67864841122cda377ff24618983014214d07625812df3bffd",
        "id": "694e4eae54b01",
        "source": "website"
    },
    {
        "id": "694e4fbba3f9f",
        "token": "3a3c0a5a875c05b9153812228a9fb43c",
        "timestamp": "2025-12-26T09:04:44.433Z",
        "source": "shortlink",
        "uuid": "0883fb77-a6b4-4185-9ffc-0eb085261754",
        "expires_at": "2025-12-26T11:04:44Z"
    }
]