[
  {
    "id": "d9c0da3066214",
    "token": "fJz8805Tlk5RmMp5xzxHL9NKRi8LQI",
    "timestamp": "2026-01-27T18:39:37Z",
    "source": "telegram",
    "uuid": "62f998bd-e92e-4cf4-b2b4-876a9b3eccbd",
    "githubSignature": "5947ab2021ec6d31054600be81ae9183973cb7c7a4cd15ae52090483151195d3"
  },
  {
    "token": "d0c4ad3f14a4714b9d12632cd337e5f1",
    "timestamp": "2026-01-27T20:40:40Z",
    "uuid": "88ad9772-27bf-4096-bda4-82ce0bb36847",
    "watch_time": 120,
    "video_id": "JYxQHCOezPE",
    "ip_address": "180.245.31.59",
    "user_agent": "Mozilla/5.0 (Linux; Android 15; Infinix X6886) AppleWebKit/537.36 (KHTML, like Gecko) Chrome/145.0.7632.19 Mobile Safari/537.36",
    "pow_verified": true,
    "request_count": 0,
    "session_hash": "418693fcae609b931090b49c5b11bcc94e618b8cfc2b1ae724db3a9a81cecc39",
    "id": "697922c9ee67f",
    "source": "website"
  },
  {
    "token": "5f992ba909c55c21676c048195dcb13d",
    "timestamp": "2026-01-27T20:44:20Z",
    "uuid": "614505a9-9a71-4076-8569-40b00e98dc39",
    "watch_time": 240,
    "video_id": "bryR8uDRCt8",
    "ip_address": "180.245.31.59",
    "user_agent": "Mozilla/5.0 (Linux; Android 15; Infinix X6886) AppleWebKit/537.36 (KHTML, like Gecko) Chrome/145.0.7632.19 Mobile Safari/537.36",
    "pow_verified": true,
    "request_count": 0,
    "session_hash": "5ccf7bb8600d4f222cf637260f92509eede1589152a502a79c7716d274162b9c",
    "id": "697923a42a392",
    "source": "website"
  }
]
