[
  {
    "token": "a812cb9ac7505e986bf4f52393bde7a7",
    "timestamp": "2026-01-21T14:36:13Z",
    "uuid": "7e27cbad-5dd2-4243-b8ce-f5727e6a9337",
    "watch_time": 300,
    "video_id": "HKF4Sgqcjts",
    "ip_address": "103.155.193.104",
    "user_agent": "Mozilla/5.0 (Windows NT 10.0; Win64; x64) AppleWebKit/537.36 (KHTML, like Gecko) Chrome/144.0.0.0 Safari/537.36",
    "pow_verified": true,
    "request_count": 0,
    "session_hash": "6ab73eb282a5143d5a7b4abca8400aeb4b494b23afa0581e7d78dab941109846",
    "id": "6970e460c098f",
    "source": "website"
  },
  {
    "id": "6970ffd09a1d5",
    "token": "50b83c5ccb87a1b22d9a81ab64ae76d1",
    "timestamp": "2026-01-21T16:33:13.891Z",
    "source": "shortlink",
    "uuid": "c2b7e520-f4a7-421f-ace4-936741b805d0",
    "expires_at": "2026-01-21T18:33:13Z"
  },
  {
    "id": "69710d40ea436",
    "token": "d73c9e1c6cda539825400e38ff5223d8",
    "timestamp": "2026-01-21T17:30:33.185Z",
    "source": "shortlink",
    "uuid": "9c076cb7-10a3-49ba-8906-d171d929530f",
    "expires_at": "2026-01-21T19:30:33Z"
  }
]
