[
    {
        "token": "b8161627c5e9241cc3018836dd35490d",
        "timestamp": "2026-06-12T09:52:26Z",
        "uuid": "2f04a4fb-0cd7-4032-8048-23ef01cfab42",
        "watch_time": 300,
        "video_id": "LaYy1LEw6tc",
        "ip_address": "2409:40f0:2421:8512:9c46:5ff:fe1a:994f",
        "user_agent": "Mozilla/5.0 (Linux; Android 10; K) AppleWebKit/537.36 (KHTML, like Gecko) Chrome/148.0.0.0 Mobile Safari/537.36",
        "pow_verified": true,
        "request_count": 0,
        "session_hash": "e867697d1fabd20d8fedf92a24d884b541f0cacc4620d0db735e793fa884bfb6",
        "id": "6a2bd6da389f6",
        "source": "website"
    }
]