[
  {
    "id": "694c51688ef17",
    "token": "da28e662b88032e5d976668fb976ac31",
    "timestamp": "2025-12-24T20:47:30.491Z",
    "source": "shortlink",
    "uuid": "04b17c05-b0f4-4384-8d02-20607b3b8d7a",
    "expires_at": "2025-12-24T22:47:30Z"
  },
  {
    "id": "694c51f860c19",
    "token": "f6b365297676cfdadd9e3f8807c9598a",
    "timestamp": "2025-12-24T20:49:46.554Z",
    "source": "shortlink",
    "uuid": "ff87a003-536e-4ace-b154-c3b92c5a8311",
    "expires_at": "2025-12-24T22:49:46Z"
  },
  {
    "id": "694c5aa9a3eed",
    "token": "adbe467c29d38617d2d9142a4ca480a2",
    "timestamp": "2025-12-24T21:26:35.352Z",
    "source": "shortlink",
    "uuid": "0c29ff35-04c6-4023-8fb9-e415656c3c7d",
    "expires_at": "2025-12-24T23:26:35Z"
  }
]
