[
    {
        "token": "9e309898032f55af72b67cbe1351241c",
        "timestamp": "2026-02-05T08:41:50Z",
        "uuid": "7cea6348-7a14-409d-b75e-04f0f54d85c1",
        "watch_time": 300,
        "video_id": "ky2YLjJhEWs",
        "ip_address": "2001:448a:20b0:1cd3:e069:2106:2830:bae",
        "user_agent": "Mozilla/5.0 (Windows NT 10.0; Win64; x64) AppleWebKit/537.36 (KHTML, like Gecko) Chrome/137.0.0.0 Safari/537.36",
        "pow_verified": true,
        "request_count": 0,
        "session_hash": "05c75ade39fcb2fedd7821d98db6b0e89f9185ad71c84d4735163e42c3bafb12",
        "id": "698457ce3c119",
        "source": "website"
    },
    {
        "id": "f779d3b32cf94",
        "token": "HYaYbMAs4tYFF0s3KaoME8Gm6vF8tX",
        "timestamp": "2026-02-05T09:45:21Z",
        "source": "telegram",
        "uuid": "95be8b88-91b9-4d78-b57b-216657b16203",
        "githubSignature": "e5504b2b5bf78570517da7eb2893c080bf49f56f26d85e39d9b9329031253932"
    }
]