[
  {
    "token": "6659d85fade096c116becccd4a1b3829",
    "timestamp": "2025-12-04T03:02:20Z",
    "uuid": "ff5ddbc0-b4be-4293-b20b-891da0866711",
    "watch_time": 180,
    "video_id": "ky2YLjJhEWs",
    "ip_address": "2409:40d4:15a:de59:706e:4dff:fe24:b06d",
    "user_agent": "Mozilla/5.0 (Android 16; Mobile; rv:145.0) Gecko/145.0 Firefox/145.0",
    "pow_verified": true,
    "request_count": 0,
    "session_hash": "c4b816fe1341a5e4f5df8904a9d6ab982a41e0ecb9bace28065196ef78bd1ca9",
    "id": "6930f9bd08968",
    "source": "website"
  },
  {
    "id": "693108d8af926",
    "token": "412675501c5119c262609a0bfc6a33ec",
    "timestamp": "2025-12-04T04:06:42.137Z",
    "source": "shortlink",
    "uuid": "29f35e65-969f-4525-9ab9-d0e99d718913",
    "expires_at": "2025-12-04T06:06:42Z"
  }
]
