[
  {
    "token": "ce1d594a592426ec54452c8c3c8a2554",
    "timestamp": "2026-05-15T00:27:04Z",
    "uuid": "29d5d829-9e51-417c-9f2b-1c945a7ad66a",
    "watch_time": 300,
    "video_id": "LaYy1LEw6tc",
    "ip_address": "103.168.255.66",
    "user_agent": "Mozilla/5.0 (Linux; Android 10; K) AppleWebKit/537.36 (KHTML, like Gecko) Chrome/137.0.0.0 Mobile Safari/537.36",
    "pow_verified": true,
    "request_count": 0,
    "session_hash": "240403d78fd075b55860e4a906bf734c75e3dbafa78900d1c1dccd4aa742f102",
    "id": "6a0668590ceeb",
    "source": "website"
  },
  {
    "token": "62ac331259bfb8856b278aa252ac83e5",
    "timestamp": "2026-05-15T02:12:43Z",
    "uuid": "83b9d6e2-b3d9-4a33-a5f6-fbbf0a4d4ff1",
    "watch_time": 240,
    "video_id": "bryR8uDRCt8",
    "ip_address": "2409:40f0:2405:a91:4c47:9bff:fea7:e0f7",
    "user_agent": "Mozilla/5.0 (Linux; Android 10; K) AppleWebKit/537.36 (KHTML, like Gecko) Chrome/148.0.0.0 Mobile Safari/537.36",
    "pow_verified": true,
    "request_count": 0,
    "session_hash": "108512b102969d2a70e0a92a9ab9bceccd899c9a590dac39a49699cf2d588a1d",
    "id": "6a06811c32f8b",
    "source": "website"
  },
  {
    "id": "f9b02315393e4",
    "token": "AMZNnGAUCFBxzY9txetjWq6sVGtPtX",
    "timestamp": "2026-05-15T03:31:58Z",
    "source": "telegram",
    "uuid": "d6659c0d-51dc-4312-8f75-83b0491ae74c",
    "githubSignature": "f08aadf6c137c2e904cbad285e8a49fae3ccb1d47eabf66cd54fcf25da37b41d"
  }
]
