[
    {
        "token": "930eb012e1f1713e8e871d997d2d941b",
        "timestamp": "2026-01-12T06:58:34Z",
        "uuid": "41d0600d-1a32-449e-84c0-b9fca23214b5",
        "watch_time": 180,
        "video_id": "zk_PBZ8iIOc",
        "ip_address": "36.90.243.97",
        "user_agent": "Mozilla/5.0 (Linux; Android 10; K) AppleWebKit/537.36 (KHTML, like Gecko) Chrome/143.0.0.0 Mobile Safari/537.36",
        "pow_verified": true,
        "request_count": 0,
        "session_hash": "f13a0d00ef6edb2f91b15bd52d292b41d276b776d81efb1cb8682aabb0badb64",
        "id": "69649b9a85a7f",
        "source": "website"
    },
    {
        "token": "a26cf667072e35ba733c99269e8a8202",
        "timestamp": "2026-01-12T09:22:40Z",
        "uuid": "77681b16-ab26-48f2-95d0-74cc04504b0e",
        "watch_time": 240,
        "video_id": "bryR8uDRCt8",
        "ip_address": "105.235.131.156",
        "user_agent": "Mozilla/5.0 (Linux; Android 10; K) AppleWebKit/537.36 (KHTML, like Gecko) Chrome/127.0.0.0 Mobile Safari/537.36",
        "pow_verified": true,
        "request_count": 0,
        "session_hash": "b011a548ee5a19b5adfc3d470870a0979dd158c16b4da417087694db3eda00dc",
        "id": "6964bd60d59a7",
        "source": "website"
    }
]