[
    {
        "token": "944abbf7bec75a159d18f01ce1009c88",
        "timestamp": "2026-04-06T17:54:25Z",
        "uuid": "d643f691-cc58-446d-8538-4847d7dfc86c",
        "watch_time": 300,
        "video_id": "bryR8uDRCt8",
        "ip_address": "196.176.207.238",
        "user_agent": "Mozilla/5.0 (Windows NT 10.0; Win64; x64) AppleWebKit/537.36 (KHTML, like Gecko) Chrome/146.0.0.0 Safari/537.36 Edg/146.0.0.0",
        "pow_verified": true,
        "request_count": 0,
        "session_hash": "c2438c42468fc79f47ddc59608e8d1e451f94e8ff73713d9e1476d646cc6bed6",
        "id": "69d3f3513f101",
        "source": "website"
    },
    {
        "id": "c3b57f953c4d4",
        "token": "y4SqDkYj85r3my69E6S66sU5Av9nHJ",
        "timestamp": "2026-04-06T19:00:39Z",
        "source": "telegram",
        "uuid": "4ec1460d-6ee7-43d8-928f-5ec72a6b005a",
        "githubSignature": "ac98bc00af7cd209da289e55d93e94ec83ea2bfcc76c166b59d519495f2b7016"
    },
    {
        "token": "eaa7e32b90c35a338b6f6896a005acd9",
        "timestamp": "2026-04-06T21:16:48Z",
        "uuid": "a088985f-8d8b-476d-bb0b-04ee2a63e02d",
        "watch_time": 180,
        "video_id": "bryR8uDRCt8",
        "ip_address": "196.176.207.238",
        "user_agent": "Mozilla/5.0 (Windows NT 10.0; Win64; x64) AppleWebKit/537.36 (KHTML, like Gecko) Chrome/146.0.0.0 Safari/537.36 Edg/146.0.0.0",
        "pow_verified": true,
        "request_count": 0,
        "session_hash": "5a0ef25218cb23f00810b1ddc486b2fcd23f38cafea6bb89c7b551c7b655b5e8",
        "id": "69d422c10b485",
        "source": "website"
    },
    {
        "token": "45000b54aa7426aab45ad1cf7332e7cf",
        "timestamp": "2026-04-06T21:42:41Z",
        "uuid": "554fd668-8b27-44d7-ad60-34ddb335c253",
        "watch_time": 180,
        "video_id": "HKF4Sgqcjts",
        "ip_address": "2001:448a:d050:3183:6101:aabc:d87a:71fc",
        "user_agent": "Mozilla/5.0 (Linux; Android 10; K) AppleWebKit/537.36 (KHTML, like Gecko) Chrome/146.0.0.0 Mobile Safari/537.36",
        "pow_verified": true,
        "request_count": 0,
        "session_hash": "6a0a86e1807dd6dfb965099eb8f49ccff9648802a241dba8e88479fad34a9ee7",
        "id": "69d428d1a59b1",
        "source": "website"
    }
]