[
    {
        "id": "693617acdfa7b",
        "token": "3906e2a43fd5c1fcc1d170320066b705",
        "timestamp": "2025-12-08T00:11:20.028Z",
        "source": "shortlink",
        "uuid": "f5832a50-439b-4178-9a0f-0bac6c29d249",
        "expires_at": "2025-12-08T02:11:20Z"
    },
    {
        "token": "d5689b2da74b243d2e3a9a00c4506b67",
        "timestamp": "2025-12-08T00:18:19Z",
        "uuid": "8e886cdb-da4f-4465-93df-f03ac8fba24c",
        "watch_time": 300,
        "video_id": "ky2YLjJhEWs",
        "ip_address": "180.241.31.1",
        "user_agent": "Mozilla/5.0 (Linux; Android 10; K) AppleWebKit/537.36 (KHTML, like Gecko) Chrome/139.0.0.0 Mobile Safari/537.36",
        "pow_verified": true,
        "request_count": 0,
        "session_hash": "ec2130ba2bba51772f40962aec3bec13aad15937156bdcc6497aaf22342000e2",
        "id": "6936194b5db24",
        "source": "website"
    },
    {
        "token": "261a6da2b95cba6e63b7bd5cbf43e5e4",
        "timestamp": "2025-12-08T01:41:13Z",
        "uuid": "b981f24e-f4de-4f30-a0a3-280df0ac27b5",
        "watch_time": 180,
        "video_id": "ky2YLjJhEWs",
        "ip_address": "2409:40d4:1249:242:381a:8fff:fe37:321a",
        "user_agent": "Mozilla/5.0 (Android 16; Mobile; rv:145.0) Gecko/145.0 Firefox/145.0",
        "pow_verified": true,
        "request_count": 0,
        "session_hash": "eccd1ddcdd74eec33c1145fff9c091182cce129bc83516ebf9baa50a28160575",
        "id": "69362cbb5d5df",
        "source": "website"
    },
    {
        "token": "80584fa9fe0ddfcff69b7441bd526634",
        "timestamp": "2025-12-08T01:50:53Z",
        "uuid": "2756b54e-34da-4e20-a229-bfbf171a8ace",
        "watch_time": 300,
        "video_id": "tQ3iTPxNO0U",
        "ip_address": "2402:800:634c:c395:bd30:6fb6:7ab4:2e4d",
        "user_agent": "Mozilla/5.0 (Windows NT 10.0; Win64; x64) AppleWebKit/537.36 (KHTML, like Gecko) Chrome/142.0.0.0 Safari/537.36",
        "pow_verified": true,
        "request_count": 0,
        "session_hash": "fa1aa1fd6f984a4627e3a3878b184b9fe2753d028cc3e243fa8606251ddf4394",
        "id": "69362efd54b2a",
        "source": "website"
    }
]