[
    {
        "id": "693ff87ac8044",
        "token": "4488770ac361629ec36927e8caeaab30",
        "timestamp": "2025-12-15T12:00:43.858Z",
        "source": "shortlink",
        "uuid": "41f75de5-3ede-4e2e-904f-f720c73cc4e9",
        "expires_at": "2025-12-15T14:00:43Z"
    },
    {
        "token": "b083306f4b7471b741f9e07746df555e",
        "timestamp": "2025-12-15T13:05:55Z",
        "uuid": "09f120b5-521c-40d7-a2a5-8d8628d53408",
        "watch_time": 120,
        "video_id": "zk_PBZ8iIOc",
        "ip_address": "2409:40f4:1007:befd:b0b1:2cff:fe64:3d3e",
        "user_agent": "Mozilla/5.0 (Linux; Android 10; K) AppleWebKit/537.36 (KHTML, like Gecko) Chrome/137.0.0.0 Mobile Safari/537.36",
        "pow_verified": true,
        "request_count": 0,
        "session_hash": "b1f58c3684ed5fb018d767fb48b528f6717bf844a9cce96fdf4ec0d2d750af83",
        "id": "694007b364103",
        "source": "website"
    },
    {
        "token": "665738febf7b59c5f20f590046ebdf49",
        "timestamp": "2025-12-15T13:11:01Z",
        "uuid": "dd808532-9f99-492b-9d79-c8eeee03d623",
        "watch_time": 240,
        "video_id": "ky2YLjJhEWs",
        "ip_address": "197.144.1.237",
        "user_agent": "Mozilla/5.0 (Linux; Android 10; K) AppleWebKit/537.36 (KHTML, like Gecko) Chrome/124.0.0.0 Mobile Safari/537.36",
        "pow_verified": true,
        "request_count": 0,
        "session_hash": "fa5f777d7e0bab7738bbca925dd152fdb453aeb641e2cc8f200dd2d1efdcd282",
        "id": "694008e56d9c1",
        "source": "website"
    },
    {
        "id": "694009b85a5fa",
        "token": "09d53224a74efb3b6a8094afe1a4104d",
        "timestamp": "2025-12-15T13:14:23.483Z",
        "source": "shortlink",
        "uuid": "c456e66c-51a9-4a1e-b90d-d8732f0d4605",
        "expires_at": "2025-12-15T15:14:23Z"
    },
    {
        "id": "69400a161ebb3",
        "token": "c08948413e50ac0870bf3dfa29608ca6",
        "timestamp": "2025-12-15T13:16:00.717Z",
        "source": "shortlink",
        "uuid": "15a810c5-1e1a-48d3-91b1-ab149e3efb1d",
        "expires_at": "2025-12-15T15:16:00Z"
    },
    {
        "id": "69400ae9b103e",
        "token": "480c90278d464e6c3ef2a48547ed71eb",
        "timestamp": "2025-12-15T13:19:32.430Z",
        "source": "shortlink",
        "uuid": "0e87b14d-996a-48f4-a039-427a6545a2da",
        "expires_at": "2025-12-15T15:19:32Z"
    },
    {
        "token": "f7987bbc189242dfebb2a69697f54056",
        "timestamp": "2025-12-15T13:30:41Z",
        "uuid": "2cc52989-59a3-467f-a567-f383af7acaed",
        "watch_time": 240,
        "video_id": "zk_PBZ8iIOc",
        "ip_address": "2001:448a:20b0:1da6:b8a8:71b0:ad25:f0d4",
        "user_agent": "Mozilla/5.0 (Windows NT 10.0; Win64; x64) AppleWebKit/537.36 (KHTML, like Gecko) Chrome/143.0.0.0 Safari/537.36 Edg/143.0.0.0",
        "pow_verified": true,
        "request_count": 0,
        "session_hash": "f6edba15cedeccbb73dec51ed3c6a72ccf8c98e37117f6ba0b40254dc0db59db",
        "id": "69400d81e5e10",
        "source": "website"
    },
    {
        "token": "c5cc59a78912edad15b569f4af0be91e",
        "timestamp": "2025-12-15T13:45:04Z",
        "uuid": "71726132-77d9-48eb-adc3-b034f8864e17",
        "watch_time": 120,
        "video_id": "HKF4Sgqcjts",
        "ip_address": "197.144.1.237",
        "user_agent": "Mozilla/5.0 (Linux; Android 10; K) AppleWebKit/537.36 (KHTML, like Gecko) Chrome/124.0.0.0 Mobile Safari/537.36",
        "pow_verified": true,
        "request_count": 0,
        "session_hash": "470a478de2b382c46ae6c8d38f627f9f654d352c11c0322a91582890f71f14fc",
        "id": "694010e063562",
        "source": "website"
    },
    {
        "token": "94e98046ebbb48ed6f317a50efea3b64",
        "timestamp": "2025-12-15T14:02:18Z",
        "uuid": "00e6fd65-3316-4f61-af16-b1e17825124d",
        "watch_time": 240,
        "video_id": "HKF4Sgqcjts",
        "ip_address": "64.188.73.201",
        "user_agent": "Mozilla/5.0 (X11; Linux x86_64) AppleWebKit/537.36 (KHTML, like Gecko) Chrome/143.0.0.0 Safari/537.36",
        "pow_verified": true,
        "request_count": 0,
        "session_hash": "fefeb127007b4f1352abfd4dd8202a99c37f3063a8793037eb29f345959b367a",
        "id": "694014eaf193f",
        "source": "website"
    }
]