[
  {
    "token": "ed7c40eb5d060124da86d774405d51be",
    "timestamp": "2025-12-07T06:37:35Z",
    "uuid": "0a2a5c51-7501-4442-8daa-3a7de30a0c86",
    "watch_time": 300,
    "video_id": "tQ3iTPxNO0U",
    "ip_address": "84.110.132.205",
    "user_agent": "Mozilla/5.0 (Linux; Android 10; K) AppleWebKit/537.36 (KHTML, like Gecko) Chrome/142.0.0.0 Mobile Safari/537.36",
    "pow_verified": true,
    "request_count": 0,
    "session_hash": "e4f345f0b8b1df3234bdaf632a746192d5575c47f41330835e8fd0e007d9457d",
    "id": "693520af53f12",
    "source": "website"
  },
  {
    "token": "ad0e692a0867f899401602ff32c0c4c7",
    "timestamp": "2025-12-07T07:02:19Z",
    "uuid": "b38e937c-5bf5-44e7-98f1-81a52f9757c6",
    "watch_time": 180,
    "video_id": "tQ3iTPxNO0U",
    "ip_address": "45.83.89.74",
    "user_agent": "Mozilla/5.0 (Macintosh; Intel Mac OS X 14) AppleWebKit/620.26.13 (KHTML, like Gecko) Version/17.6.67 Safari/620.26.13",
    "pow_verified": true,
    "request_count": 0,
    "session_hash": "d22b7ab5b040d98c5f7f2233020b5ed6dace9dd7c100d0812bcddcc84b13d09e",
    "id": "6935267c31c15",
    "source": "website"
  },
  {
    "token": "afa03ab47b950a6aef52ba60ed0bbeb6",
    "timestamp": "2025-12-07T08:38:13Z",
    "uuid": "a3fde0a7-180c-4ca9-8adf-f70445a7b5a7",
    "watch_time": 120,
    "video_id": "tQ3iTPxNO0U",
    "ip_address": "2409:40d4:3111:a92d:1838:99ff:fe04:a1be",
    "user_agent": "Mozilla/5.0 (Android 16; Mobile; rv:145.0) Gecko/145.0 Firefox/145.0",
    "pow_verified": true,
    "request_count": 0,
    "session_hash": "d06002c04cac1c6c497f75aa471298c3cae6cc2339d518cde9b492385d5b23de",
    "id": "69353cf5bdbe7",
    "source": "website"
  }
]
