[
    {
        "token": "0b3d41255d1e8924d8b7e12e275ecb89",
        "timestamp": "2026-05-30T04:27:05Z",
        "uuid": "a95f1055-7e13-46dc-82f5-f646dabd53bf",
        "watch_time": 240,
        "video_id": "HKF4Sgqcjts",
        "ip_address": "2401:4900:60ff:4b19:a82a:1aff:fec2:99a7",
        "user_agent": "Mozilla/5.0 (Linux; Android 10; K) AppleWebKit/537.36 (KHTML, like Gecko) Chrome/148.0.0.0 Mobile Safari/537.36",
        "pow_verified": true,
        "request_count": 0,
        "session_hash": "241078becca12ca098f668b40b74f918459c59568968272ee8dd234398074357",
        "id": "6a1a6719536d2",
        "source": "website"
    },
    {
        "token": "0ca6b1a0319cf290db33d6f02e49df24",
        "timestamp": "2026-05-30T04:34:39Z",
        "uuid": "71eb2100-acc2-4ffd-ad6e-0d43ccd8e4dc",
        "watch_time": 300,
        "video_id": "LaYy1LEw6tc",
        "ip_address": "2401:4900:60ff:4b19:a82a:1aff:fec2:99a7",
        "user_agent": "Mozilla/5.0 (Linux; Android 10; K) AppleWebKit/537.36 (KHTML, like Gecko) Chrome/148.0.0.0 Mobile Safari/537.36",
        "pow_verified": true,
        "request_count": 0,
        "session_hash": "7272fdf0bf4806ad13cb2a2b6bc2d5faf82c2c2272bcada4a9156e4472074d5b",
        "id": "6a1a68df8cef8",
        "source": "website"
    }
]