[
    {
        "token": "bfb5ea1fb7cc3a21b1f70ae307954dbd",
        "timestamp": "2026-04-12T22:51:34Z",
        "uuid": "5a195531-dd5b-4224-8d1f-237a7b8f18e3",
        "watch_time": 300,
        "video_id": "bryR8uDRCt8",
        "ip_address": "114.10.22.189",
        "user_agent": "Mozilla/5.0 (Linux; Android 10; K) AppleWebKit/537.36 (KHTML, like Gecko) Chrome/146.0.0.0 Mobile Safari/537.36",
        "pow_verified": true,
        "request_count": 0,
        "session_hash": "1fd657b984b161afa8c0640259693dbad03c2bdf6e7daaeb5a38d6cde96260dc",
        "id": "69dc21f6e170e",
        "source": "website"
    },
    {
        "token": "5ec424adca227e2695601a4c29bd981c",
        "timestamp": "2026-04-13T01:49:25Z",
        "uuid": "4abfa60d-f915-474f-86f1-d9d545bdfeb4",
        "watch_time": 120,
        "video_id": "bryR8uDRCt8",
        "ip_address": "196.176.207.238",
        "user_agent": "Mozilla/5.0 (Linux; Android 10; K) AppleWebKit/537.36 (KHTML, like Gecko) Chrome/147.0.0.0 Mobile Safari/537.36",
        "pow_verified": true,
        "request_count": 0,
        "session_hash": "2b7ed183cc602e6b65cd67d7facf5aee21ee559ad3c485ab7721923078b59f42",
        "id": "69dc4ba5835ce",
        "source": "website"
    },
    {
        "id": "cb52c80cee0d4",
        "token": "g2K9PvWDnf9J5fprdN5YJtQCN40ker",
        "timestamp": "2026-04-13T02:42:33Z",
        "source": "telegram",
        "uuid": "258d21e6-0b0c-48c1-96c0-c1dd313679d4",
        "githubSignature": "c81d3a87e308c7bbc7786a58b3d9baf6201d6664993b5b9414d15bd2b8a23df4"
    }
]