[
    {
        "token": "746b52e6ad63134ae564da28fd96cade",
        "timestamp": "2026-02-06T11:10:56Z",
        "uuid": "34d0abe6-d1d9-4ebf-ac11-f75105a8dadb",
        "watch_time": 180,
        "video_id": "zk_PBZ8iIOc",
        "ip_address": "197.49.144.239",
        "user_agent": "Mozilla/5.0 (Linux; Android 10; K) AppleWebKit/537.36 (KHTML, like Gecko) Chrome/144.0.0.0 Mobile Safari/537.36",
        "pow_verified": true,
        "request_count": 0,
        "session_hash": "56d1d30b36e1ce1932debf5765bb5a019d455e4343ebed5486a1a67ca49a14fd",
        "id": "6985cc40a94d8",
        "source": "website"
    },
    {
        "token": "033a4d0efd883cec4c54b0c14fc238ca",
        "timestamp": "2026-02-06T13:21:38Z",
        "uuid": "d0aed5db-5f8f-4c72-87ef-135fbe624edb",
        "watch_time": 300,
        "video_id": "bryR8uDRCt8",
        "ip_address": "105.105.23.247",
        "user_agent": "Mozilla/5.0 (X11; Linux x86_64) AppleWebKit/537.36 (KHTML, like Gecko) Chrome/144.0.0.0 Safari/537.36",
        "pow_verified": true,
        "request_count": 0,
        "session_hash": "0795b3e0ae6a5f7cef2864df69bf0e22b42cc8a3833c30fd9c660b8ed0663436",
        "id": "6985eae309cf4",
        "source": "website"
    }
]