[
    {
        "token": "447efb5b2a281d6c45ecfa8f7dc145b4",
        "timestamp": "2026-03-18T16:43:32Z",
        "uuid": "69c4e465-5bb8-45a5-a1dd-608e68fb52dc",
        "watch_time": 180,
        "video_id": "bryR8uDRCt8",
        "ip_address": "2404:c0:1c90:1ed7:60e9:baff:feaf:c5f4",
        "user_agent": "Mozilla/5.0 (Linux; Android 10; K) AppleWebKit/537.36 (KHTML, like Gecko) Chrome/145.0.0.0 Mobile Safari/537.36",
        "pow_verified": true,
        "request_count": 0,
        "session_hash": "392d93b36ac67ac2734d169d632028751e239d4cdd8b05154b3332468091bae8",
        "id": "69bad634872c3",
        "source": "website"
    },
    {
        "token": "e4a0366d8d40187c666988dadf08217a",
        "timestamp": "2026-03-18T17:46:33Z",
        "uuid": "bf5a119b-067b-43aa-be55-3b83b2834a5e",
        "watch_time": 300,
        "video_id": "bryR8uDRCt8",
        "ip_address": "2404:c0:1c90:1ed7:60e9:baff:feaf:c5f4",
        "user_agent": "Mozilla/5.0 (Linux; Android 10; K) AppleWebKit/537.36 (KHTML, like Gecko) Chrome/145.0.0.0 Mobile Safari/537.36",
        "pow_verified": true,
        "request_count": 0,
        "session_hash": "aa11699231df05ca02b4ec5104807d44bd0e1d9c99560e97044c1ad70aa021f1",
        "id": "69bae4f98e728",
        "source": "website"
    },
    {
        "token": "83394cdded841743300b5bff0d21e2f8",
        "timestamp": "2026-03-18T18:01:37Z",
        "uuid": "59b37ea1-8ab2-4132-acff-90dd2874e93f",
        "watch_time": 180,
        "video_id": "bryR8uDRCt8",
        "ip_address": "2404:c0:1c90:1ed7:60e9:baff:feaf:c5f4",
        "user_agent": "Mozilla/5.0 (Linux; Android 10; K) AppleWebKit/537.36 (KHTML, like Gecko) Chrome/145.0.0.0 Mobile Safari/537.36",
        "pow_verified": true,
        "request_count": 0,
        "session_hash": "565fe9829ddfa4e984e69f3cc8e588060d295aef4841e4050cb8fda27898efcc",
        "id": "69bae8819c9f1",
        "source": "website"
    }
]