[
  {
    "token": "bfb5ea1fb7cc3a21b1f70ae307954dbd",
    "timestamp": "2026-04-12T22:51:34Z",
    "uuid": "5a195531-dd5b-4224-8d1f-237a7b8f18e3",
    "watch_time": 300,
    "video_id": "bryR8uDRCt8",
    "ip_address": "114.10.22.189",
    "user_agent": "Mozilla/5.0 (Linux; Android 10; K) AppleWebKit/537.36 (KHTML, like Gecko) Chrome/146.0.0.0 Mobile Safari/537.36",
    "pow_verified": true,
    "request_count": 0,
    "session_hash": "1fd657b984b161afa8c0640259693dbad03c2bdf6e7daaeb5a38d6cde96260dc",
    "id": "69dc21f6e170e",
    "source": "website"
  }
]
