[
  {
    "token": "c7815860655f66214257dfb6f020ed9b",
    "timestamp": "2026-05-11T06:57:36Z",
    "uuid": "569a181b-5539-4ee9-8af1-0192a5f0e7e6",
    "watch_time": 180,
    "video_id": "LaYy1LEw6tc",
    "ip_address": "157.85.210.45",
    "user_agent": "Mozilla/5.0 (Linux; Android 10; K) AppleWebKit/537.36 (KHTML, like Gecko) Chrome/147.0.0.0 Mobile Safari/537.36",
    "pow_verified": true,
    "request_count": 0,
    "session_hash": "a2efb5783edc6f474fdaabbc3157b6f6ea1f6e44aa0a248276328c35487b1b5d",
    "id": "6a017de03bfef",
    "source": "website"
  },
  {
    "token": "26f2bf110c3499e998bf6e155c3e6819",
    "timestamp": "2026-05-11T09:00:56Z",
    "uuid": "a15e004b-1442-4fa3-be06-272bec704962",
    "watch_time": 120,
    "video_id": "LaYy1LEw6tc",
    "ip_address": "223.196.198.79",
    "user_agent": "Mozilla/5.0 (Linux; Android 10; K) AppleWebKit/537.36 (KHTML, like Gecko) Chrome/148.0.0.0 Mobile Safari/537.36",
    "pow_verified": true,
    "request_count": 0,
    "session_hash": "859dc032ad540b014a80df1893532f9ca820d9c2e98db96378d18cbfca1e3dbf",
    "id": "6a019ac88b174",
    "source": "website"
  }
]
