[
  {
    "token": "fa2a055a6103401a76ce7023aa6f0be8",
    "timestamp": "2026-01-20T23:10:58Z",
    "uuid": "57ccfde5-fc66-4332-84ad-16c63deb873c",
    "watch_time": 240,
    "video_id": "ky2YLjJhEWs",
    "ip_address": "103.121.212.2",
    "user_agent": "Mozilla/5.0 (Linux; Android 11; CPH2269 Build/RP1A.200720.011) AppleWebKit/537.36 (KHTML, like Gecko) Chrome/143.0.7499.192 Mobile Safari/537.36",
    "pow_verified": true,
    "request_count": 0,
    "session_hash": "562b270ed5e3db5110c742c24ea610e77f84a1c5f0cbe617f380fe3842164c3e",
    "id": "69700b8326cb0",
    "source": "website"
  }
]
