[
    {
        "token": "687e3c0c5c4a2d267018683d87b43e2a",
        "timestamp": "2026-01-20T17:24:13Z",
        "uuid": "bed28806-c6b6-465b-bd45-32cd5afe97cf",
        "watch_time": 240,
        "video_id": "HKF4Sgqcjts",
        "ip_address": "112.79.21.151",
        "user_agent": "Mozilla/5.0 (Linux; Android 10; K) AppleWebKit/537.36 (KHTML, like Gecko) Chrome/143.0.0.0 Mobile Safari/537.36",
        "pow_verified": true,
        "request_count": 0,
        "session_hash": "c5f250ba88d61b217cf42ba874c7550e7c3078264e0d1334c6a3e86a04741e71",
        "id": "696fba3dc29a2",
        "source": "website"
    },
    {
        "token": "4dfd74f95bed244010e6c02ecc5563ea",
        "timestamp": "2026-01-20T17:42:10Z",
        "uuid": "5b64867e-f127-4bb0-b099-2859c0bc2e96",
        "watch_time": 180,
        "video_id": "zk_PBZ8iIOc",
        "ip_address": "114.122.12.43",
        "user_agent": "Mozilla/5.0 (Linux; Android 10; K) AppleWebKit/537.36 (KHTML, like Gecko) Chrome/141.0.0.0 Mobile Safari/537.36 AlohaBrowser/7.12.2",
        "pow_verified": true,
        "request_count": 0,
        "session_hash": "40ee7e6e9d3c6f251e57690abc7e2c5bb543d5c67eefb6ca485cc6366cfb75d8",
        "id": "696fbe72bc604",
        "source": "website"
    },
    {
        "token": "4d0eabaa7e69059f2e455189d70ab3bd",
        "timestamp": "2026-01-20T17:47:18Z",
        "uuid": "1c9e93c0-a3d7-45e2-98eb-f859e882ab29",
        "watch_time": 240,
        "video_id": "tQ3iTPxNO0U",
        "ip_address": "112.79.21.151",
        "user_agent": "Mozilla/5.0 (Linux; Android 10; K) AppleWebKit/537.36 (KHTML, like Gecko) Chrome/127.0.0.0 Mobile Safari/537.36",
        "pow_verified": true,
        "request_count": 0,
        "session_hash": "b569031ff0ae9b219ea6b01b18bf4e125072a847845ae344269d0fe982ff2159",
        "id": "696fbfa6bad3a",
        "source": "website"
    },
    {
        "id": "e2dd3944703a4",
        "token": "dCespKjvhgYc0ol3KAX8Hl5mtUc4mX",
        "timestamp": "2026-01-20T18:38:04Z",
        "source": "telegram",
        "uuid": "507161a2-0d83-4aa4-81f0-ccd15a509696",
        "githubSignature": "20cedd42d4d7267999fe4608be049d239d0cee5b45b4a82ed40eb6683809f426"
    },
    {
        "token": "e958a3ad2b515a2e97c2a1868c962f0a",
        "timestamp": "2026-01-20T20:03:43Z",
        "uuid": "177354eb-f607-45ad-9016-0570f97dc793",
        "watch_time": 180,
        "video_id": "tQ3iTPxNO0U",
        "ip_address": "129.222.109.36",
        "user_agent": "Mozilla/5.0 (X11; Linux x86_64) AppleWebKit/537.36 (KHTML, like Gecko) Chrome/144.0.0.0 Safari/537.36",
        "pow_verified": true,
        "request_count": 0,
        "session_hash": "17bfa1ca1aaea9f7f9edf63aca031affd562b520b6bda7f407c657d4a6fcf1ca",
        "id": "696fdf9f57aa9",
        "source": "website"
    }
]