[
  {
    "token": "530fe5fb6170fa2eeca5050bd12bf809",
    "timestamp": "2026-01-01T08:19:02Z",
    "uuid": "78d19235-ca32-4cbb-9686-3ae1ac9ac141",
    "watch_time": 240,
    "video_id": "zk_PBZ8iIOc",
    "ip_address": "114.10.69.249",
    "user_agent": "Mozilla/5.0 (Linux; Android 10; K) AppleWebKit/537.36 (KHTML, like Gecko) Chrome/137.0.0.0 Mobile Safari/537.36",
    "pow_verified": true,
    "request_count": 0,
    "session_hash": "503f116809513cfb91a6f392326ab686ec1eac2ae05eef0b8f1a442814947b5e",
    "id": "69562df65756b",
    "source": "website"
  },
  {
    "id": "69562ef9a3118",
    "token": "467ec9124171fcca999612b9a9915b48",
    "timestamp": "2026-01-01T08:23:07.424Z",
    "source": "shortlink",
    "uuid": "9f54e813-4c93-4e33-bf0a-a1ba0e4bf291",
    "expires_at": "2026-01-01T10:23:07Z"
  },
  {
    "id": "69563b044257e",
    "token": "ac099d571b7534cf07703cf214bff621",
    "timestamp": "2026-01-01T09:14:36.459Z",
    "source": "shortlink",
    "uuid": "7f608db0-a341-4ef5-b5e4-b4e2eda89aae",
    "expires_at": "2026-01-01T11:14:36Z"
  },
  {
    "token": "43bb5a7fc684d77b9425775b8b869605",
    "timestamp": "2026-01-01T09:22:30Z",
    "uuid": "541813bd-9ac7-4300-99d7-01f8a335adc3",
    "watch_time": 180,
    "video_id": "JYxQHCOezPE",
    "ip_address": "110.137.82.136",
    "user_agent": "Mozilla/5.0 (Windows NT 10.0; Win64; x64) AppleWebKit/537.36 (KHTML, like Gecko) Chrome/143.0.0.0 Safari/537.36",
    "pow_verified": true,
    "request_count": 0,
    "session_hash": "b22650bad67b752b2ac507b320bd4a76c22bacbb21918f1932873e9a35ed6e20",
    "id": "69563cd6dbd6b",
    "source": "website"
  }
]
