[
  {
    "token": "fc419de85ec679995654a62acccea5b7",
    "timestamp": "2025-11-14T19:34:10Z",
    "uuid": "4c62b80e-766e-4373-96e6-1f66441e1f0e",
    "watch_time": 180,
    "video_id": "HKF4Sgqcjts",
    "ip_address": "105.235.131.32",
    "user_agent": "Mozilla/5.0 (Linux; Android 10; K) AppleWebKit/537.36 (KHTML, like Gecko) Chrome/135.0.0.0 Mobile Safari/537.36",
    "pow_verified": true,
    "request_count": 0,
    "session_hash": "c462e33f69305c4d47e33b38317a5bc9eddc31f178a5196183517a3074f08aa8",
    "id": "69178432d9cb2",
    "source": "website"
  },
  {
    "id": "6917940d06d92",
    "token": "2b34f75723881ed9f7fb43adcfa34b35",
    "timestamp": "2025-11-14T20:41:27.876Z",
    "source": "shortlink",
    "uuid": "cc3c7e17-cadb-4110-a6e7-73a845b5c62d",
    "expires_at": "2025-11-14T22:41:27Z"
  }
]
